<?xml version = '1.0' encoding = 'UTF-8'?>
<Relation class="oracle.dbtools.crest.model.design.logical.Relation" name="SrvyRspdr_AssessMode_FK" directorySegmentName="seg_15" id="9EC0772C-3DD9-BFE2-09A7-2A2BA6DDD1B9">
<createdBy>leads</createdBy>
<createdTime>2026-03-12 07:49:06 UTC</createdTime>
<ownerDesignName>leadsuser</ownerDesignName>
<importedID>B022AEED-543E-F296-EEE8-061884A134EB</importedID>
<engineerTo>
<item key="D0ADEC0C-0B6F-9EE3-0047-804409B8E385" value="true"/>
</engineerTo>
<sourcePk>E7563FD9-41C0-E733-8700-964AF9C2B555</sourcePk>
<identifying>false</identifying>
<optionalSource>true</optionalSource>
<optionalTarget>false</optionalTarget>
<sourceCardinality>1</sourceCardinality>
<sourceEntity>096CDA21-1DF5-BBFB-2D79-ADA53FFD6A1A</sourceEntity>
<targetCardinalityString>*</targetCardinalityString>
<targetEntity>354CBB63-3F0B-1B06-77FC-8166AE21E487</targetEntity>
<transferable>true</transferable>
<deleteRule>NO ACTION</deleteRule>
</Relation>
