<?xml version = '1.0' encoding = 'UTF-8'?>
<Relation class="oracle.dbtools.crest.model.design.logical.Relation" name="StdQstBnkAss_Ordinal_FK" directorySegmentName="seg_17" id="6D6DC5B9-6A19-C818-54E9-8913713E6B09">
<createdBy>leads</createdBy>
<createdTime>2026-03-12 07:49:00 UTC</createdTime>
<ownerDesignName>leadsuser</ownerDesignName>
<importedID>D35D7144-D28F-D2E1-A141-D96F84E249FE</importedID>
<engineerTo>
<item key="D0ADEC0C-0B6F-9EE3-0047-804409B8E385" value="true"/>
</engineerTo>
<sourcePk>81751D7A-69D0-96E9-A775-783C1A737E24</sourcePk>
<identifying>false</identifying>
<optionalSource>true</optionalSource>
<optionalTarget>false</optionalTarget>
<sourceCardinality>1</sourceCardinality>
<sourceEntity>1A1DD98A-E124-9663-D550-31822E0123F7</sourceEntity>
<targetCardinalityString>*</targetCardinalityString>
<targetEntity>18F14F76-CAEC-3F41-66A1-98575821E229</targetEntity>
<transferable>true</transferable>
<deleteRule>NO ACTION</deleteRule>
</Relation>
