<?xml version = '1.0' encoding = 'UTF-8'?>
<Diagram class="oracle.dbtools.crest.swingui.relational.DPVRelationalSubView" name="From_LM_Logical - Employee_Exceptions" id="5EF79C0B-6108-3B0E-F9FA-7A700B542A17">
<createdBy>leads</createdBy>
<modifiedBy>leads</modifiedBy>
<createdTime>2026-03-23 07:31:42 UTC</createdTime>
<autoRoute>false</autoRoute>
<boxInbox>true</boxInbox>
<showLegend>false</showLegend>
<showLabels>false</showLabels>
<showRelAttributes>false</showRelAttributes>
<gridEnabled>false</gridEnabled>
<showGrid>false</showGrid>
<diagramColor>-1</diagramColor>
<display>false</display>
<generatorId>1D67B586-E261-4423-EE76-76340C16A71D</generatorId>
<notation>1</notation>
<objectViews>
<OView class="oracle.dbtools.crest.swingui.relational.TVTable" oid="1371099A-1439-8437-7F09-0DE8F72B7913" otype="Table" vid="4C3172B2-F6E5-D9F0-83DE-BE1247D838D5">
<hideElementsInCurrentOnly>false</hideElementsInCurrentOnly>
<bounds x="1487" y="219" width="258" height="151"/>
<generatorID>EAB62E28-7637-CC9D-115B-0104FE92FE78</generatorID>
</OView>
<OView class="oracle.dbtools.crest.swingui.relational.TVTable" oid="4D0B79B4-F89A-AA8A-9B4A-747C0F6E7835" otype="Table" vid="DBFE4FCA-234E-1DF8-377F-4D0DF118BD84">
<hideElementsInCurrentOnly>false</hideElementsInCurrentOnly>
<bounds x="11" y="123" width="447" height="488"/>
<generatorID>7A0F8D3D-32DF-220D-BDD3-BDD9630A3290</generatorID>
</OView>
<OView class="oracle.dbtools.crest.swingui.relational.TVTable" oid="5B55AE0C-0FF7-B97C-3B24-66C46D243DCD" otype="Table" vid="66AAD5AA-C547-762A-46F3-6A23BE55F784">
<hideElementsInCurrentOnly>false</hideElementsInCurrentOnly>
<bounds x="823" y="8" width="390" height="162"/>
<generatorID>EFB1C2C5-39FF-80AE-DF6D-12C40D201146</generatorID>
</OView>
<OView class="oracle.dbtools.crest.swingui.relational.TVTable" oid="E1ED8105-49CB-B7F1-6EEC-3966A088B011" otype="Table" vid="8CA71B01-B32E-02E8-A826-6E30CFE2962D">
<hideElementsInCurrentOnly>false</hideElementsInCurrentOnly>
<bounds x="1315" y="585" width="218" height="111"/>
<generatorID>D5E8074E-F41F-5C08-F6F5-4C493DB758E3</generatorID>
</OView>
</objectViews>
<connectors>
<Connector class="oracle.dbtools.crest.swingui.relational.TVFKRelation" oid="37FE2B2F-B0E9-E133-CB9B-9350F3877775" otype="FKIndexAssociation" vid_source="4C3172B2-F6E5-D9F0-83DE-BE1247D838D5" vid_target="66AAD5AA-C547-762A-46F3-6A23BE55F784">
<hideElementsInCurrentOnly>false</hideElementsInCurrentOnly>
<backgroundColor>-16777216</backgroundColor>
<lineWidth>1</lineWidth>
<points>
<point x="1487" y="280"/>
<point x="823" y="144"/>
</points>
</Connector>
<Connector class="oracle.dbtools.crest.swingui.relational.TVFKRelation" oid="5B38075D-543D-AB93-E7D2-E11554D821BB" otype="FKIndexAssociation" vid_source="DBFE4FCA-234E-1DF8-377F-4D0DF118BD84" vid_target="66AAD5AA-C547-762A-46F3-6A23BE55F784">
<hideElementsInCurrentOnly>false</hideElementsInCurrentOnly>
<backgroundColor>-16777216</backgroundColor>
<lineWidth>1</lineWidth>
<points>
<point x="458" y="123"/>
<point x="823" y="110"/>
</points>
</Connector>
<Connector class="oracle.dbtools.crest.swingui.relational.TVFKRelation" oid="E8A06C4C-A391-C1FF-10CC-8DA15D085AC7" otype="FKIndexAssociation" vid_source="8CA71B01-B32E-02E8-A826-6E30CFE2962D" vid_target="66AAD5AA-C547-762A-46F3-6A23BE55F784">
<hideElementsInCurrentOnly>false</hideElementsInCurrentOnly>
<backgroundColor>-16777216</backgroundColor>
<lineWidth>1</lineWidth>
<points>
<point x="1315" y="596"/>
<point x="823" y="169"/>
</points>
</Connector>
</connectors>
</Diagram>
