<?xml version = '1.0' encoding = 'UTF-8'?>
<Diagram class="oracle.dbtools.crest.swingui.relational.DPVRelationalSubView" name="From_LM_Logical - Classroom_Markcard" id="79A4917C-652A-A8E4-F070-187A48992CCE">
<createdBy>leads</createdBy>
<modifiedBy>leads</modifiedBy>
<createdTime>2026-03-23 07:31:41 UTC</createdTime>
<autoRoute>false</autoRoute>
<boxInbox>true</boxInbox>
<showLegend>false</showLegend>
<showLabels>false</showLabels>
<showRelAttributes>false</showRelAttributes>
<gridEnabled>false</gridEnabled>
<showGrid>false</showGrid>
<diagramColor>-1</diagramColor>
<display>false</display>
<generatorId>189FAE7E-1145-8409-F1B3-37EC39F2F9F4</generatorId>
<notation>1</notation>
<objectViews>
<OView class="oracle.dbtools.crest.swingui.relational.TVTable" oid="06AE5EBC-4230-E202-C12E-CA351EC2A5AE" otype="Table" vid="B2F39D76-26E4-6529-A866-B4D0DC7269EF">
<hideElementsInCurrentOnly>false</hideElementsInCurrentOnly>
<bounds x="0" y="1039" width="428" height="331"/>
<generatorID>344E42E3-6933-A970-26AF-00320223E9D5</generatorID>
</OView>
<OView class="oracle.dbtools.crest.swingui.relational.TVTable" oid="0C5CFE88-FE38-CBB6-9F44-3BC9013BB34A" otype="Table" vid="B432C446-685E-8118-0B87-3EF3C04631BF">
<hideElementsInCurrentOnly>false</hideElementsInCurrentOnly>
<bounds x="1057" y="1044" width="444" height="240"/>
<generatorID>8D0B0977-2AA7-EFA8-69AF-2FF699B6741D</generatorID>
</OView>
<OView class="oracle.dbtools.crest.swingui.relational.TVTable" oid="173A22FA-F3FA-D821-1FBA-E3B857D29C39" otype="Table" vid="56DF83AF-3665-104E-85B4-92B7C8B1BF3F">
<hideElementsInCurrentOnly>false</hideElementsInCurrentOnly>
<bounds x="1653" y="1074" width="542" height="240"/>
<generatorID>6C7992FD-DCEB-37CA-E5E1-BF5D6977CE64</generatorID>
</OView>
<OView class="oracle.dbtools.crest.swingui.relational.TVTable" oid="1C2D5E6A-2D21-9A0C-4D89-2CE09789EB63" otype="Table" vid="C3F2C83A-0A03-314B-B41C-001C97FC4B34">
<hideElementsInCurrentOnly>false</hideElementsInCurrentOnly>
<bounds x="3551" y="0" width="271" height="402"/>
<generatorID>5E4919A6-8DAA-E417-12BA-95EF47EA2692</generatorID>
</OView>
<OView class="oracle.dbtools.crest.swingui.relational.TVTable" oid="26954F48-00E7-B302-875F-4B47075ACEF2" otype="Table" vid="B735748C-5124-F6ED-005C-20C13B3441B1">
<hideElementsInCurrentOnly>false</hideElementsInCurrentOnly>
<bounds x="906" y="1688" width="256" height="125"/>
<generatorID>3845421D-ECB8-87B5-696C-CA5762246D39</generatorID>
</OView>
<OView class="oracle.dbtools.crest.swingui.relational.TVTable" oid="2BA3AB6A-C975-35A6-5021-1FC322E8AE6C" otype="Table" vid="AA93D5A3-02D5-C622-8083-E4FA183000B2">
<hideElementsInCurrentOnly>false</hideElementsInCurrentOnly>
<bounds x="2735" y="0" width="386" height="188"/>
<generatorID>0B9F512F-C35E-DE5C-E846-61CB4FA44E52</generatorID>
</OView>
<OView class="oracle.dbtools.crest.swingui.relational.TVTable" oid="33E67B4F-51BF-4E2B-CB9B-735BF727449D" otype="Table" vid="6D6317DA-44EF-A756-0EC0-EA91C59F47C8">
<hideElementsInCurrentOnly>false</hideElementsInCurrentOnly>
<bounds x="1468" y="2412" width="234" height="138"/>
<generatorID>1E43E006-FA77-FDFC-F569-9316D07CA442</generatorID>
</OView>
<OView class="oracle.dbtools.crest.swingui.relational.TVTable" oid="38CA7EBB-9626-9B1C-01C2-BCF3E4491B8C" otype="Table" vid="E4ADAFA7-7993-E7C0-6E99-F0EBF6F4C43F">
<hideElementsInCurrentOnly>false</hideElementsInCurrentOnly>
<bounds x="2364" y="2407" width="240" height="111"/>
<generatorID>08975756-F4B6-16E3-0C1B-D54E1E6314D9</generatorID>
</OView>
<OView class="oracle.dbtools.crest.swingui.relational.TVTable" oid="415C796A-7A90-B7CA-9AD5-CAF778300D97" otype="Table" vid="BE4321F5-42BD-6777-870B-299897B5DEEB">
<hideElementsInCurrentOnly>false</hideElementsInCurrentOnly>
<bounds x="1032" y="2092" width="234" height="125"/>
<generatorID>B435564C-59F9-AAE5-8604-38FE0E2F7FD4</generatorID>
</OView>
<OView class="oracle.dbtools.crest.swingui.relational.TVTable" oid="4A562C52-91EC-AA77-65A0-0B21C3DA7AB5" otype="Table" vid="DD4F4BB5-CF62-D62E-4744-EEF2B5E4C96A">
<hideElementsInCurrentOnly>false</hideElementsInCurrentOnly>
<bounds x="0" y="2095" width="234" height="98"/>
<generatorID>A660CFF6-E9A3-8306-76F2-03E565757B09</generatorID>
</OView>
<OView class="oracle.dbtools.crest.swingui.relational.TVTable" oid="4C4CD88F-BC3C-B191-3450-24E300E8A2C3" otype="Table" vid="EF9E83AB-D9CE-C610-6AF9-2D88CAE5BF84">
<hideElementsInCurrentOnly>false</hideElementsInCurrentOnly>
<bounds x="1982" y="2431" width="234" height="98"/>
<generatorID>8B32C741-4CC5-6CB3-E3C8-2FD3865E52D1</generatorID>
</OView>
<OView class="oracle.dbtools.crest.swingui.relational.TVTable" oid="50BE3178-B111-2EF9-6A30-6A9660C0A6D4" otype="Table" vid="386E014F-6611-2D63-FDE7-95E73A16772B">
<hideElementsInCurrentOnly>false</hideElementsInCurrentOnly>
<bounds x="520" y="0" width="420" height="240"/>
<generatorID>85F053D2-7C79-414A-E68B-C20D368157DE</generatorID>
</OView>
<OView class="oracle.dbtools.crest.swingui.relational.TVTable" oid="52801159-C22F-027D-1900-85C7DA107F19" otype="Table" vid="927C5CC2-2227-D7D4-82D8-4E2BE921A317">
<hideElementsInCurrentOnly>false</hideElementsInCurrentOnly>
<bounds x="383" y="2118" width="234" height="98"/>
<generatorID>E9202AFA-95BD-22AA-B76A-0B67D3B41904</generatorID>
</OView>
<OView class="oracle.dbtools.crest.swingui.relational.TVTable" oid="635A1150-1830-C596-E161-903ED8775C70" otype="Table" vid="5C66BF63-067C-1A42-715D-BD24198F0AAA">
<hideElementsInCurrentOnly>false</hideElementsInCurrentOnly>
<bounds x="2190" y="0" width="368" height="188"/>
<generatorID>2B004000-DBF2-CDC8-AF70-A408CF50D4F1</generatorID>
</OView>
<OView class="oracle.dbtools.crest.swingui.relational.TVTable" oid="66E660ED-6976-5A05-46E3-9CEC08A0A159" otype="Table" vid="C7B173EB-649C-B128-AB08-14E43E042660">
<hideElementsInCurrentOnly>false</hideElementsInCurrentOnly>
<bounds x="1383" y="2124" width="241" height="138"/>
<generatorID>D410035B-57FA-744C-BBD6-3511303EB22D</generatorID>
</OView>
<OView class="oracle.dbtools.crest.swingui.relational.TVTable" oid="67082105-99E4-0B53-ABE8-A7C8FEA5384A" otype="Table" vid="A7BC0044-8620-238E-B052-3FDB7F0346A3">
<hideElementsInCurrentOnly>false</hideElementsInCurrentOnly>
<bounds x="1416" y="546" width="638" height="292"/>
<generatorID>A485F169-C3A1-581A-8A9A-70A082598DB4</generatorID>
</OView>
<OView class="oracle.dbtools.crest.swingui.relational.TVTable" oid="74894763-4653-DF35-A9D0-481B8F82382F" otype="Table" vid="D9E7CE60-0340-6CE2-FECF-ADCB687AC73A">
<hideElementsInCurrentOnly>false</hideElementsInCurrentOnly>
<bounds x="1036" y="0" width="452" height="240"/>
<generatorID>7FB9AF10-F4D1-BD88-1ACA-98742DF65F92</generatorID>
</OView>
<OView class="oracle.dbtools.crest.swingui.relational.TVTable" oid="74B3180F-E45C-68E0-1CBD-15DF5FEF494F" otype="Table" vid="A2B20561-DE2A-E6BA-E742-879918EB320C">
<hideElementsInCurrentOnly>false</hideElementsInCurrentOnly>
<bounds x="7" y="0" width="434" height="227"/>
<generatorID>EB398047-135A-BF20-98ED-267845DCD728</generatorID>
</OView>
<OView class="oracle.dbtools.crest.swingui.relational.TVTable" oid="7FC1FAF5-BC00-6EEB-9731-150A2A90F27E" otype="Table" vid="9B4D6AC3-1456-2BA8-F08B-273B777A7E2A">
<hideElementsInCurrentOnly>false</hideElementsInCurrentOnly>
<bounds x="2228" y="561" width="501" height="201"/>
<generatorID>AEEFC1D0-8472-3832-AFD7-778AF3A25FA5</generatorID>
</OView>
<OView class="oracle.dbtools.crest.swingui.relational.TVTable" oid="9920947A-5D02-3E79-4F49-C8112887E0D4" otype="Table" vid="CB608AA3-00EB-16DE-4354-BC686D696C19">
<hideElementsInCurrentOnly>false</hideElementsInCurrentOnly>
<bounds x="365" y="2406" width="234" height="125"/>
<generatorID>1AF57C25-A198-43F8-FEC6-BD2F7834D132</generatorID>
</OView>
<OView class="oracle.dbtools.crest.swingui.relational.TVTable" oid="A0BA42F6-4F3C-7149-3789-3207D30913C7" otype="Table" vid="FB039351-B4A0-F538-4B8B-8F6DC8F249B2">
<hideElementsInCurrentOnly>false</hideElementsInCurrentOnly>
<bounds x="2629" y="2141" width="234" height="98"/>
<generatorID>F2291DB0-B307-276C-0713-9DC883290836</generatorID>
</OView>
<OView class="oracle.dbtools.crest.swingui.relational.TVTable" oid="A219EA87-F929-C519-3D8A-A04CA1688606" otype="Table" vid="BC89369A-A176-92E8-4375-B85AC6B892D0">
<hideElementsInCurrentOnly>false</hideElementsInCurrentOnly>
<bounds x="778" y="2385" width="235" height="152"/>
<generatorID>40C8E6FE-8BE3-8A67-4DD6-9C1951E13A53</generatorID>
</OView>
<OView class="oracle.dbtools.crest.swingui.relational.TVTable" oid="AB4E411A-10A7-14C6-6A6A-1331F43CA391" otype="Table" vid="49354C52-3926-3594-CB4B-7DA72E65D14E">
<hideElementsInCurrentOnly>false</hideElementsInCurrentOnly>
<bounds x="411" y="1685" width="393" height="214"/>
<generatorID>1BF3A260-9EE0-5A24-1B15-C3DEB5229EE0</generatorID>
</OView>
<OView class="oracle.dbtools.crest.swingui.relational.TVTable" oid="AC4D7418-2465-B893-7B3B-DF91F19CD6F8" otype="Table" vid="E3EEC2DC-DC2B-D990-7820-6452EAE5CC03">
<hideElementsInCurrentOnly>false</hideElementsInCurrentOnly>
<bounds x="6" y="1687" width="241" height="125"/>
<generatorID>4EDE4245-E482-6ECE-423C-15DEEF21BE8F</generatorID>
</OView>
<OView class="oracle.dbtools.crest.swingui.relational.TVTable" oid="AC6E975A-E10C-7DA9-CE35-15AB648AB53F" otype="Table" vid="3E87ED0F-AF70-3B6B-B025-71DCF30FA07C">
<hideElementsInCurrentOnly>false</hideElementsInCurrentOnly>
<bounds x="4" y="2401" width="260" height="151"/>
<generatorID>4C4D4B78-0037-25A2-037D-DB884EB32EFD</generatorID>
</OView>
<OView class="oracle.dbtools.crest.swingui.relational.TVTable" oid="B3C43AEE-85FF-8237-C50E-3038D0610DEC" otype="Table" vid="8D36E317-745F-361B-C991-5551059DABFF">
<hideElementsInCurrentOnly>false</hideElementsInCurrentOnly>
<bounds x="1208" y="2396" width="234" height="98"/>
<generatorID>B623960B-74CE-3BBA-2B81-A41C724C50D6</generatorID>
</OView>
<OView class="oracle.dbtools.crest.swingui.relational.TVTable" oid="BB61FE5B-735C-7A07-C30C-2FB447C08803" otype="Table" vid="7E02EBD7-367D-B4FB-DDEF-C434EE2C17A1">
<hideElementsInCurrentOnly>false</hideElementsInCurrentOnly>
<bounds x="538" y="1051" width="390" height="214"/>
<generatorID>7E671516-004C-24F8-634E-05697BDF5F95</generatorID>
</OView>
<OView class="oracle.dbtools.crest.swingui.relational.TVTable" oid="BCEDF83B-F6D4-E35A-A390-1F212AD18C10" otype="Table" vid="7DB9CAC1-0900-E28B-89D7-70F157D2C798">
<hideElementsInCurrentOnly>false</hideElementsInCurrentOnly>
<bounds x="1796" y="2124" width="234" height="98"/>
<generatorID>EA37D42A-D53E-A63A-C41E-54C3CAD8410E</generatorID>
</OView>
<OView class="oracle.dbtools.crest.swingui.relational.TVTable" oid="C5E10AF5-646F-1848-405F-D8996E275ADD" otype="Table" vid="F2BB0BB9-9C54-6BA9-58A2-658E8AFC55FD">
<hideElementsInCurrentOnly>false</hideElementsInCurrentOnly>
<bounds x="1405" y="1653" width="271" height="203"/>
<generatorID>B5A83C44-790A-6310-5D55-84EAA6C9C7F0</generatorID>
</OView>
<OView class="oracle.dbtools.crest.swingui.relational.TVTable" oid="C6F6D206-FEF6-2D0A-7896-E7BE89C3BDA2" otype="Table" vid="64D78C5C-398E-3F88-E026-222A3DD14985">
<hideElementsInCurrentOnly>false</hideElementsInCurrentOnly>
<bounds x="0" y="575" width="494" height="266"/>
<generatorID>C30A2895-99ED-F6CC-FE47-D3DD912D791A</generatorID>
</OView>
<OView class="oracle.dbtools.crest.swingui.relational.TVTable" oid="D7463B55-5078-91B7-A266-D36FD800D327" otype="Table" vid="F0E32C7A-CBA2-746F-3199-A7BE1C31A4EB">
<hideElementsInCurrentOnly>false</hideElementsInCurrentOnly>
<bounds x="636" y="570" width="586" height="266"/>
<generatorID>4EC4DA73-F50B-26ED-6996-52479E80C24D</generatorID>
</OView>
<OView class="oracle.dbtools.crest.swingui.relational.TVTable" oid="DCA9DB06-1CA5-650B-0A71-E6A90E092F68" otype="Table" vid="A91919A4-DA6F-3998-CC63-6A0AAAB7AA58">
<hideElementsInCurrentOnly>false</hideElementsInCurrentOnly>
<bounds x="2742" y="2416" width="213" height="98"/>
<generatorID>C3BE2159-250A-C7D5-6DC4-0A1093FCF5D2</generatorID>
</OView>
<OView class="oracle.dbtools.crest.swingui.relational.TVTable" oid="E289B831-BB79-8E9D-EAC9-DB758B0C1D86" otype="Table" vid="B8C6FE8F-86D3-D280-A906-C9920AB4BDBB">
<hideElementsInCurrentOnly>false</hideElementsInCurrentOnly>
<bounds x="3012" y="471" width="622" height="410"/>
<generatorID>992ABC47-48CB-CDF6-C0E9-95462FD9C882</generatorID>
</OView>
<OView class="oracle.dbtools.crest.swingui.relational.TVTable" oid="F0B3F36D-F1DA-2AEF-BC91-0882954F6701" otype="Table" vid="26599D9D-6C65-973C-5A2E-E323B9607EB2">
<hideElementsInCurrentOnly>false</hideElementsInCurrentOnly>
<bounds x="3296" y="1477" width="271" height="410"/>
<generatorID>D234F6DE-6A44-B6EA-8606-CB2712234D02</generatorID>
</OView>
<OView class="oracle.dbtools.crest.swingui.relational.TVTable" oid="FDD54FC9-92D5-B806-F905-B70D1129ECDD" otype="Table" vid="3493D9D2-FFCA-7466-EE0B-13F1201B2A89">
<hideElementsInCurrentOnly>false</hideElementsInCurrentOnly>
<bounds x="723" y="2120" width="188" height="85"/>
<generatorID>8CFDCA25-931F-F2EA-60E6-F9A5068986A8</generatorID>
</OView>
</objectViews>
<connectors>
<Connector class="oracle.dbtools.crest.swingui.relational.TVFKRelation" oid="03A358E7-ABD0-E205-639D-48FBB7C0E70D" otype="FKIndexAssociation" vid_source="A91919A4-DA6F-3998-CC63-6A0AAAB7AA58" vid_target="49354C52-3926-3594-CB4B-7DA72E65D14E">
<hideElementsInCurrentOnly>false</hideElementsInCurrentOnly>
<backgroundColor>-16777216</backgroundColor>
<lineWidth>1</lineWidth>
<points>
<point x="2792" y="2416"/>
<point x="411" y="1685"/>
</points>
</Connector>
<Connector class="oracle.dbtools.crest.swingui.relational.TVFKRelation" oid="05FCA6CE-F6F4-B1B7-4745-EF58E8D3BF7F" otype="FKIndexAssociation" vid_source="CB608AA3-00EB-16DE-4354-BC686D696C19" vid_target="F0E32C7A-CBA2-746F-3199-A7BE1C31A4EB">
<hideElementsInCurrentOnly>false</hideElementsInCurrentOnly>
<backgroundColor>-16777216</backgroundColor>
<lineWidth>1</lineWidth>
<points>
<point x="473" y="2406"/>
<point x="636" y="570"/>
</points>
</Connector>
<Connector class="oracle.dbtools.crest.swingui.relational.TVFKRelation" oid="094FB144-6BCD-BA9B-2995-0F75874D60FA" otype="FKIndexAssociation" vid_source="3E87ED0F-AF70-3B6B-B025-71DCF30FA07C" vid_target="5C66BF63-067C-1A42-715D-BD24198F0AAA">
<hideElementsInCurrentOnly>false</hideElementsInCurrentOnly>
<backgroundColor>-16777216</backgroundColor>
<lineWidth>1</lineWidth>
<points>
<point x="264" y="2401"/>
<point x="2190" y="149"/>
</points>
</Connector>
<Connector class="oracle.dbtools.crest.swingui.relational.TVFKRelation" oid="0D4B36EC-1BA5-BBD3-3CF7-07C56F85C543" otype="FKIndexAssociation" vid_source="DD4F4BB5-CF62-D62E-4744-EEF2B5E4C96A" vid_target="B2F39D76-26E4-6529-A866-B4D0DC7269EF">
<hideElementsInCurrentOnly>false</hideElementsInCurrentOnly>
<backgroundColor>-16777216</backgroundColor>
<lineWidth>1</lineWidth>
<points>
<point x="177" y="2095"/>
<point x="177" y="1039"/>
</points>
</Connector>
<Connector class="oracle.dbtools.crest.swingui.relational.TVFKRelation" oid="0FA672AD-34D8-0EEE-11D8-59BDD976260C" otype="FKIndexAssociation" vid_source="3E87ED0F-AF70-3B6B-B025-71DCF30FA07C" vid_target="386E014F-6611-2D63-FDE7-95E73A16772B">
<hideElementsInCurrentOnly>false</hideElementsInCurrentOnly>
<backgroundColor>-16777216</backgroundColor>
<lineWidth>1</lineWidth>
<points>
<point x="165" y="2401"/>
<point x="520" y="190"/>
</points>
</Connector>
<Connector class="oracle.dbtools.crest.swingui.relational.TVFKRelation" oid="1240EB33-D74A-C59E-F2B2-0EE1EB82A982" otype="FKIndexAssociation" vid_source="6D6317DA-44EF-A756-0EC0-EA91C59F47C8" vid_target="A7BC0044-8620-238E-B052-3FDB7F0346A3">
<hideElementsInCurrentOnly>false</hideElementsInCurrentOnly>
<backgroundColor>-16777216</backgroundColor>
<lineWidth>1</lineWidth>
<points>
<point x="1468" y="2412"/>
<point x="1416" y="573"/>
</points>
</Connector>
<Connector class="oracle.dbtools.crest.swingui.relational.TVFKRelation" oid="12736B0F-B16F-7281-D71F-2E2085F8F0FF" otype="FKIndexAssociation" vid_source="26599D9D-6C65-973C-5A2E-E323B9607EB2" vid_target="9B4D6AC3-1456-2BA8-F08B-273B777A7E2A">
<hideElementsInCurrentOnly>false</hideElementsInCurrentOnly>
<backgroundColor>-16777216</backgroundColor>
<lineWidth>1</lineWidth>
<points>
<point x="3296" y="1477"/>
<point x="2228" y="609"/>
</points>
</Connector>
<Connector class="oracle.dbtools.crest.swingui.relational.TVFKRelation" oid="13CC13B8-302A-2752-39C8-E7D57E156AE8" otype="FKIndexAssociation" vid_source="3E87ED0F-AF70-3B6B-B025-71DCF30FA07C" vid_target="B8C6FE8F-86D3-D280-A906-C9920AB4BDBB">
<hideElementsInCurrentOnly>false</hideElementsInCurrentOnly>
<backgroundColor>-16777216</backgroundColor>
<lineWidth>1</lineWidth>
<points>
<point x="264" y="2401"/>
<point x="3012" y="625"/>
</points>
</Connector>
<Connector class="oracle.dbtools.crest.swingui.relational.TVFKRelation" oid="13DA70A4-9704-F6A1-84F7-D70B30F31424" otype="FKIndexAssociation" vid_source="BC89369A-A176-92E8-4375-B85AC6B892D0" vid_target="56DF83AF-3665-104E-85B4-92B7C8B1BF3F">
<hideElementsInCurrentOnly>false</hideElementsInCurrentOnly>
<backgroundColor>-16777216</backgroundColor>
<lineWidth>1</lineWidth>
<points>
<point x="842" y="2385"/>
<point x="1653" y="1074"/>
</points>
</Connector>
<Connector class="oracle.dbtools.crest.swingui.relational.TVFKRelation" oid="14017448-3C29-ED62-46F7-DE5614E65608" otype="FKIndexAssociation" vid_source="CB608AA3-00EB-16DE-4354-BC686D696C19" vid_target="AA93D5A3-02D5-C622-8083-E4FA183000B2">
<hideElementsInCurrentOnly>false</hideElementsInCurrentOnly>
<backgroundColor>-16777216</backgroundColor>
<lineWidth>1</lineWidth>
<points>
<point x="367" y="2406"/>
<point x="2735" y="188"/>
</points>
</Connector>
<Connector class="oracle.dbtools.crest.swingui.relational.TVFKRelation" oid="14EE4FFC-27D6-09D3-FDEF-B90ABAFB9059" otype="FKIndexAssociation" vid_source="A91919A4-DA6F-3998-CC63-6A0AAAB7AA58" vid_target="386E014F-6611-2D63-FDE7-95E73A16772B">
<hideElementsInCurrentOnly>false</hideElementsInCurrentOnly>
<backgroundColor>-16777216</backgroundColor>
<lineWidth>1</lineWidth>
<points>
<point x="2792" y="2416"/>
<point x="520" y="190"/>
</points>
</Connector>
<Connector class="oracle.dbtools.crest.swingui.relational.TVFKRelation" oid="1B742776-8190-EBD3-00CF-ACE21B35C3B8" otype="FKIndexAssociation" vid_source="E4ADAFA7-7993-E7C0-6E99-F0EBF6F4C43F" vid_target="3493D9D2-FFCA-7466-EE0B-13F1201B2A89">
<hideElementsInCurrentOnly>false</hideElementsInCurrentOnly>
<backgroundColor>-16777216</backgroundColor>
<lineWidth>1</lineWidth>
<points>
<point x="2364" y="2407"/>
<point x="803" y="2120"/>
</points>
</Connector>
<Connector class="oracle.dbtools.crest.swingui.relational.TVFKRelation" oid="1B8B1D3C-992D-E90C-24C4-D29053BCDEF1" otype="FKIndexAssociation" vid_source="927C5CC2-2227-D7D4-82D8-4E2BE921A317" vid_target="B8C6FE8F-86D3-D280-A906-C9920AB4BDBB">
<hideElementsInCurrentOnly>false</hideElementsInCurrentOnly>
<backgroundColor>-16777216</backgroundColor>
<lineWidth>1</lineWidth>
<points>
<point x="491" y="2118"/>
<point x="3012" y="471"/>
</points>
</Connector>
<Connector class="oracle.dbtools.crest.swingui.relational.TVFKRelation" oid="2155FB17-0CF6-E711-6897-705163C3B474" otype="FKIndexAssociation" vid_source="BC89369A-A176-92E8-4375-B85AC6B892D0" vid_target="49354C52-3926-3594-CB4B-7DA72E65D14E">
<hideElementsInCurrentOnly>false</hideElementsInCurrentOnly>
<backgroundColor>-16777216</backgroundColor>
<lineWidth>1</lineWidth>
<points>
<point x="778" y="2385"/>
<point x="578" y="1685"/>
</points>
</Connector>
<Connector class="oracle.dbtools.crest.swingui.relational.TVFKRelation" oid="224346D2-7912-E051-D499-66007D50D4FE" otype="FKIndexAssociation" vid_source="C7B173EB-649C-B128-AB08-14E43E042660" vid_target="56DF83AF-3665-104E-85B4-92B7C8B1BF3F">
<hideElementsInCurrentOnly>false</hideElementsInCurrentOnly>
<backgroundColor>-16777216</backgroundColor>
<lineWidth>1</lineWidth>
<points>
<point x="1468" y="2124"/>
<point x="1653" y="1074"/>
</points>
</Connector>
<Connector class="oracle.dbtools.crest.swingui.relational.TVFKRelation" oid="2343B383-9DD0-6AFB-4C57-D46A0064D795" otype="FKIndexAssociation" vid_source="3E87ED0F-AF70-3B6B-B025-71DCF30FA07C" vid_target="49354C52-3926-3594-CB4B-7DA72E65D14E">
<hideElementsInCurrentOnly>false</hideElementsInCurrentOnly>
<backgroundColor>-16777216</backgroundColor>
<lineWidth>1</lineWidth>
<points>
<point x="220" y="2401"/>
<point x="595" y="1685"/>
</points>
</Connector>
<Connector class="oracle.dbtools.crest.swingui.relational.TVFKRelation" oid="25EF6034-F9A8-7E6D-C842-A1794342232B" otype="FKIndexAssociation" vid_source="BC89369A-A176-92E8-4375-B85AC6B892D0" vid_target="B2F39D76-26E4-6529-A866-B4D0DC7269EF">
<hideElementsInCurrentOnly>false</hideElementsInCurrentOnly>
<backgroundColor>-16777216</backgroundColor>
<lineWidth>1</lineWidth>
<points>
<point x="872" y="2385"/>
<point x="221" y="1039"/>
</points>
</Connector>
<Connector class="oracle.dbtools.crest.swingui.relational.TVFKRelation" oid="265756EF-11D3-5451-C4DE-B09EA56C19EC" otype="FKIndexAssociation" vid_source="3E87ED0F-AF70-3B6B-B025-71DCF30FA07C" vid_target="AA93D5A3-02D5-C622-8083-E4FA183000B2">
<hideElementsInCurrentOnly>false</hideElementsInCurrentOnly>
<backgroundColor>-16777216</backgroundColor>
<lineWidth>1</lineWidth>
<points>
<point x="264" y="2401"/>
<point x="2735" y="134"/>
</points>
</Connector>
<Connector class="oracle.dbtools.crest.swingui.relational.TVFKRelation" oid="2689F370-D40B-41FF-65E6-D89B57CB3817" otype="FKIndexAssociation" vid_source="BC89369A-A176-92E8-4375-B85AC6B892D0" vid_target="A7BC0044-8620-238E-B052-3FDB7F0346A3">
<hideElementsInCurrentOnly>false</hideElementsInCurrentOnly>
<backgroundColor>-16777216</backgroundColor>
<lineWidth>1</lineWidth>
<points>
<point x="778" y="2385"/>
<point x="1416" y="591"/>
</points>
</Connector>
<Connector class="oracle.dbtools.crest.swingui.relational.TVFKRelation" oid="2C138F93-C956-FDE9-A7C9-3EE35E33BA5E" otype="FKIndexAssociation" vid_source="F2BB0BB9-9C54-6BA9-58A2-658E8AFC55FD" vid_target="B2F39D76-26E4-6529-A866-B4D0DC7269EF">
<hideElementsInCurrentOnly>false</hideElementsInCurrentOnly>
<backgroundColor>-16777216</backgroundColor>
<lineWidth>1</lineWidth>
<points>
<point x="1452" y="1653"/>
<point x="252" y="1039"/>
</points>
</Connector>
<Connector class="oracle.dbtools.crest.swingui.relational.TVFKRelation" oid="2DC8C758-0517-56EA-3E26-045A3AAB994C" otype="FKIndexAssociation" vid_source="B735748C-5124-F6ED-005C-20C13B3441B1" vid_target="F2BB0BB9-9C54-6BA9-58A2-658E8AFC55FD">
<hideElementsInCurrentOnly>false</hideElementsInCurrentOnly>
<backgroundColor>-16777216</backgroundColor>
<lineWidth>1</lineWidth>
<points>
<point x="906" y="1688"/>
<point x="1455" y="1653"/>
</points>
</Connector>
<Connector class="oracle.dbtools.crest.swingui.relational.TVFKRelation" oid="2FD43528-D533-F464-8D31-76642C434730" otype="FKIndexAssociation" vid_source="8D36E317-745F-361B-C991-5551059DABFF" vid_target="B8C6FE8F-86D3-D280-A906-C9920AB4BDBB">
<hideElementsInCurrentOnly>false</hideElementsInCurrentOnly>
<backgroundColor>-16777216</backgroundColor>
<lineWidth>1</lineWidth>
<points>
<point x="1300" y="2396"/>
<point x="3012" y="471"/>
</points>
</Connector>
<Connector class="oracle.dbtools.crest.swingui.relational.TVFKRelation" oid="3400B852-0E52-5C98-24AA-6A23EBB5BBD6" otype="FKIndexAssociation" vid_source="E3EEC2DC-DC2B-D990-7820-6452EAE5CC03" vid_target="B432C446-685E-8118-0B87-3EF3C04631BF">
<hideElementsInCurrentOnly>false</hideElementsInCurrentOnly>
<backgroundColor>-16777216</backgroundColor>
<lineWidth>1</lineWidth>
<points>
<point x="212" y="1687"/>
<point x="1166" y="1044"/>
</points>
</Connector>
<Connector class="oracle.dbtools.crest.swingui.relational.TVFKRelation" oid="35E8CC00-BE4C-4566-B636-3BA55EE5CB92" otype="FKIndexAssociation" vid_source="CB608AA3-00EB-16DE-4354-BC686D696C19" vid_target="64D78C5C-398E-3F88-E026-222A3DD14985">
<hideElementsInCurrentOnly>false</hideElementsInCurrentOnly>
<backgroundColor>-16777216</backgroundColor>
<lineWidth>1</lineWidth>
<points>
<point x="474" y="2406"/>
<point x="214" y="575"/>
</points>
</Connector>
<Connector class="oracle.dbtools.crest.swingui.relational.TVFKRelation" oid="36050259-BA4A-A3D3-50E9-3ABFAD14BA16" otype="FKIndexAssociation" vid_source="BC89369A-A176-92E8-4375-B85AC6B892D0" vid_target="7E02EBD7-367D-B4FB-DDEF-C434EE2C17A1">
<hideElementsInCurrentOnly>false</hideElementsInCurrentOnly>
<backgroundColor>-16777216</backgroundColor>
<lineWidth>1</lineWidth>
<points>
<point x="778" y="2385"/>
<point x="672" y="1051"/>
</points>
</Connector>
<Connector class="oracle.dbtools.crest.swingui.relational.TVFKRelation" oid="36E4B36E-DB2D-4920-B523-BBB0C21D023A" otype="FKIndexAssociation" vid_source="BC89369A-A176-92E8-4375-B85AC6B892D0" vid_target="64D78C5C-398E-3F88-E026-222A3DD14985">
<hideElementsInCurrentOnly>false</hideElementsInCurrentOnly>
<backgroundColor>-16777216</backgroundColor>
<lineWidth>1</lineWidth>
<points>
<point x="872" y="2385"/>
<point x="232" y="575"/>
</points>
</Connector>
<Connector class="oracle.dbtools.crest.swingui.relational.TVFKRelation" oid="3F36063C-C6B8-4491-4019-5689DB43550E" otype="FKIndexAssociation" vid_source="BC89369A-A176-92E8-4375-B85AC6B892D0" vid_target="AA93D5A3-02D5-C622-8083-E4FA183000B2">
<hideElementsInCurrentOnly>false</hideElementsInCurrentOnly>
<backgroundColor>-16777216</backgroundColor>
<lineWidth>1</lineWidth>
<points>
<point x="873" y="2385"/>
<point x="2735" y="188"/>
</points>
</Connector>
<Connector class="oracle.dbtools.crest.swingui.relational.TVFKRelation" oid="3F4EF122-491B-B6AD-A832-FF5F5AE96304" otype="FKIndexAssociation" vid_source="BC89369A-A176-92E8-4375-B85AC6B892D0" vid_target="26599D9D-6C65-973C-5A2E-E323B9607EB2">
<hideElementsInCurrentOnly>false</hideElementsInCurrentOnly>
<backgroundColor>-16777216</backgroundColor>
<lineWidth>1</lineWidth>
<points>
<point x="873" y="2385"/>
<point x="3296" y="1477"/>
</points>
</Connector>
<Connector class="oracle.dbtools.crest.swingui.relational.TVFKRelation" oid="40320683-502C-1689-AD54-97A2B1A6ED4D" otype="FKIndexAssociation" vid_source="FB039351-B4A0-F538-4B8B-8F6DC8F249B2" vid_target="B432C446-685E-8118-0B87-3EF3C04631BF">
<hideElementsInCurrentOnly>false</hideElementsInCurrentOnly>
<backgroundColor>-16777216</backgroundColor>
<lineWidth>1</lineWidth>
<points>
<point x="2629" y="2141"/>
<point x="1194" y="1044"/>
</points>
</Connector>
<Connector class="oracle.dbtools.crest.swingui.relational.TVFKRelation" oid="404B51E6-8D13-26F9-E6CD-FDB2DD8C9954" otype="FKIndexAssociation" vid_source="7DB9CAC1-0900-E28B-89D7-70F157D2C798" vid_target="B2F39D76-26E4-6529-A866-B4D0DC7269EF">
<hideElementsInCurrentOnly>false</hideElementsInCurrentOnly>
<backgroundColor>-16777216</backgroundColor>
<lineWidth>1</lineWidth>
<points>
<point x="1796" y="2124"/>
<point x="165" y="1039"/>
</points>
</Connector>
<Connector class="oracle.dbtools.crest.swingui.relational.TVFKRelation" oid="43A17EE5-2707-A63F-EBFD-A38A95D54EF5" otype="FKIndexAssociation" vid_source="CB608AA3-00EB-16DE-4354-BC686D696C19" vid_target="26599D9D-6C65-973C-5A2E-E323B9607EB2">
<hideElementsInCurrentOnly>false</hideElementsInCurrentOnly>
<backgroundColor>-16777216</backgroundColor>
<lineWidth>1</lineWidth>
<points>
<point x="389" y="2406"/>
<point x="3296" y="1477"/>
</points>
</Connector>
<Connector class="oracle.dbtools.crest.swingui.relational.TVFKRelation" oid="446BD042-D5EA-4961-C22A-303A59B0271D" otype="FKIndexAssociation" vid_source="E3EEC2DC-DC2B-D990-7820-6452EAE5CC03" vid_target="A7BC0044-8620-238E-B052-3FDB7F0346A3">
<hideElementsInCurrentOnly>false</hideElementsInCurrentOnly>
<backgroundColor>-16777216</backgroundColor>
<lineWidth>1</lineWidth>
<points>
<point x="247" y="1687"/>
<point x="1416" y="603"/>
</points>
</Connector>
<Connector class="oracle.dbtools.crest.swingui.relational.TVFKRelation" oid="44A70359-A6F1-0107-D710-94C3657A0B17" otype="FKIndexAssociation" vid_source="CB608AA3-00EB-16DE-4354-BC686D696C19" vid_target="56DF83AF-3665-104E-85B4-92B7C8B1BF3F">
<hideElementsInCurrentOnly>false</hideElementsInCurrentOnly>
<backgroundColor>-16777216</backgroundColor>
<lineWidth>1</lineWidth>
<points>
<point x="512" y="2406"/>
<point x="1653" y="1074"/>
</points>
</Connector>
<Connector class="oracle.dbtools.crest.swingui.relational.TVFKRelation" oid="46BE8B1E-44D5-A163-F6BC-FA47F7FBBBD4" otype="FKIndexAssociation" vid_source="CB608AA3-00EB-16DE-4354-BC686D696C19" vid_target="B432C446-685E-8118-0B87-3EF3C04631BF">
<hideElementsInCurrentOnly>false</hideElementsInCurrentOnly>
<backgroundColor>-16777216</backgroundColor>
<lineWidth>1</lineWidth>
<points>
<point x="473" y="2406"/>
<point x="1057" y="1044"/>
</points>
</Connector>
<Connector class="oracle.dbtools.crest.swingui.relational.TVFKRelation" oid="55F96557-7EA5-A3EB-14F2-071951FE6189" otype="FKIndexAssociation" vid_source="EF9E83AB-D9CE-C610-6AF9-2D88CAE5BF84" vid_target="B8C6FE8F-86D3-D280-A906-C9920AB4BDBB">
<hideElementsInCurrentOnly>false</hideElementsInCurrentOnly>
<backgroundColor>-16777216</backgroundColor>
<lineWidth>1</lineWidth>
<points>
<point x="2058" y="2431"/>
<point x="3012" y="471"/>
</points>
</Connector>
<Connector class="oracle.dbtools.crest.swingui.relational.TVFKRelation" oid="587F775B-5A27-F278-C09A-67DF7A548F5B" otype="FKIndexAssociation" vid_source="C7B173EB-649C-B128-AB08-14E43E042660" vid_target="64D78C5C-398E-3F88-E026-222A3DD14985">
<hideElementsInCurrentOnly>false</hideElementsInCurrentOnly>
<backgroundColor>-16777216</backgroundColor>
<lineWidth>1</lineWidth>
<points>
<point x="1459" y="2124"/>
<point x="266" y="575"/>
</points>
</Connector>
<Connector class="oracle.dbtools.crest.swingui.relational.TVFKRelation" oid="5C7C74A3-F702-CAE2-2C76-94A6E116116B" otype="FKIndexAssociation" vid_source="CB608AA3-00EB-16DE-4354-BC686D696C19" vid_target="B2F39D76-26E4-6529-A866-B4D0DC7269EF">
<hideElementsInCurrentOnly>false</hideElementsInCurrentOnly>
<backgroundColor>-16777216</backgroundColor>
<lineWidth>1</lineWidth>
<points>
<point x="474" y="2406"/>
<point x="211" y="1039"/>
</points>
</Connector>
<Connector class="oracle.dbtools.crest.swingui.relational.TVFKRelation" oid="5DCBEB4E-927C-6D57-EFC2-6E67A5CF17E7" otype="FKIndexAssociation" vid_source="3E87ED0F-AF70-3B6B-B025-71DCF30FA07C" vid_target="A7BC0044-8620-238E-B052-3FDB7F0346A3">
<hideElementsInCurrentOnly>false</hideElementsInCurrentOnly>
<backgroundColor>-16777216</backgroundColor>
<lineWidth>1</lineWidth>
<points>
<point x="264" y="2401"/>
<point x="1416" y="628"/>
</points>
</Connector>
<Connector class="oracle.dbtools.crest.swingui.relational.TVFKRelation" oid="5ECE3527-BF47-BC1A-52E5-A9EF934FE2E1" otype="FKIndexAssociation" vid_source="6D6317DA-44EF-A756-0EC0-EA91C59F47C8" vid_target="56DF83AF-3665-104E-85B4-92B7C8B1BF3F">
<hideElementsInCurrentOnly>false</hideElementsInCurrentOnly>
<backgroundColor>-16777216</backgroundColor>
<lineWidth>1</lineWidth>
<points>
<point x="1552" y="2412"/>
<point x="1653" y="1074"/>
</points>
</Connector>
<Connector class="oracle.dbtools.crest.swingui.relational.TVFKRelation" oid="5F5D8622-A528-4EAA-B818-2C2375C05970" otype="FKIndexAssociation" vid_source="6D6317DA-44EF-A756-0EC0-EA91C59F47C8" vid_target="5C66BF63-067C-1A42-715D-BD24198F0AAA">
<hideElementsInCurrentOnly>false</hideElementsInCurrentOnly>
<backgroundColor>-16777216</backgroundColor>
<lineWidth>1</lineWidth>
<points>
<point x="1542" y="2412"/>
<point x="2190" y="188"/>
</points>
</Connector>
<Connector class="oracle.dbtools.crest.swingui.relational.TVFKRelation" oid="617833DD-18D4-3941-91E3-DB9A288D6250" otype="FKIndexAssociation" vid_source="CB608AA3-00EB-16DE-4354-BC686D696C19" vid_target="B8C6FE8F-86D3-D280-A906-C9920AB4BDBB">
<hideElementsInCurrentOnly>false</hideElementsInCurrentOnly>
<backgroundColor>-16777216</backgroundColor>
<lineWidth>1</lineWidth>
<points>
<point x="473" y="2406"/>
<point x="3012" y="471"/>
</points>
</Connector>
<Connector class="oracle.dbtools.crest.swingui.relational.TVFKRelation" oid="63E9AEB0-F7C7-53AF-1938-850386448FEF" otype="FKIndexAssociation" vid_source="BC89369A-A176-92E8-4375-B85AC6B892D0" vid_target="B8C6FE8F-86D3-D280-A906-C9920AB4BDBB">
<hideElementsInCurrentOnly>false</hideElementsInCurrentOnly>
<backgroundColor>-16777216</backgroundColor>
<lineWidth>1</lineWidth>
<points>
<point x="871" y="2385"/>
<point x="3012" y="471"/>
</points>
</Connector>
<Connector class="oracle.dbtools.crest.swingui.relational.TVFKRelation" oid="650103F6-392C-A151-91DF-7A137D9EC239" otype="FKIndexAssociation" vid_source="3E87ED0F-AF70-3B6B-B025-71DCF30FA07C" vid_target="B432C446-685E-8118-0B87-3EF3C04631BF">
<hideElementsInCurrentOnly>false</hideElementsInCurrentOnly>
<backgroundColor>-16777216</backgroundColor>
<lineWidth>1</lineWidth>
<points>
<point x="264" y="2401"/>
<point x="1178" y="1044"/>
</points>
</Connector>
<Connector class="oracle.dbtools.crest.swingui.relational.TVFKRelation" oid="677E70CF-793A-A309-987C-1AB84FE19E63" otype="FKIndexAssociation" vid_source="3E87ED0F-AF70-3B6B-B025-71DCF30FA07C" vid_target="7E02EBD7-367D-B4FB-DDEF-C434EE2C17A1">
<hideElementsInCurrentOnly>false</hideElementsInCurrentOnly>
<backgroundColor>-16777216</backgroundColor>
<lineWidth>1</lineWidth>
<points>
<point x="245" y="2401"/>
<point x="690" y="1051"/>
</points>
</Connector>
<Connector class="oracle.dbtools.crest.swingui.relational.TVFKRelation" oid="740DD918-72D9-2A74-4A2C-5FEDE9F72155" otype="FKIndexAssociation" vid_source="E3EEC2DC-DC2B-D990-7820-6452EAE5CC03" vid_target="64D78C5C-398E-3F88-E026-222A3DD14985">
<hideElementsInCurrentOnly>false</hideElementsInCurrentOnly>
<backgroundColor>-16777216</backgroundColor>
<lineWidth>1</lineWidth>
<points>
<point x="153" y="1687"/>
<point x="153" y="575"/>
</points>
</Connector>
<Connector class="oracle.dbtools.crest.swingui.relational.TVFKRelation" oid="765175D3-F43C-ADB8-6F2D-1CEFCC722F2D" otype="FKIndexAssociation" vid_source="927C5CC2-2227-D7D4-82D8-4E2BE921A317" vid_target="3493D9D2-FFCA-7466-EE0B-13F1201B2A89">
<hideElementsInCurrentOnly>false</hideElementsInCurrentOnly>
<backgroundColor>-16777216</backgroundColor>
<lineWidth>1</lineWidth>
<points>
<point x="383" y="2118"/>
<point x="818" y="2120"/>
</points>
</Connector>
<Connector class="oracle.dbtools.crest.swingui.relational.TVFKRelation" oid="768AF784-B8C1-E403-42AD-95C55965B1D7" otype="FKIndexAssociation" vid_source="BC89369A-A176-92E8-4375-B85AC6B892D0" vid_target="D9E7CE60-0340-6CE2-FECF-ADCB687AC73A">
<hideElementsInCurrentOnly>false</hideElementsInCurrentOnly>
<backgroundColor>-16777216</backgroundColor>
<lineWidth>1</lineWidth>
<points>
<point x="871" y="2385"/>
<point x="1036" y="190"/>
</points>
</Connector>
<Connector class="oracle.dbtools.crest.swingui.relational.TVFKRelation" oid="77449F0C-CAF5-A411-CC68-8886CF877F8B" otype="FKIndexAssociation" vid_source="C7B173EB-649C-B128-AB08-14E43E042660" vid_target="49354C52-3926-3594-CB4B-7DA72E65D14E">
<hideElementsInCurrentOnly>false</hideElementsInCurrentOnly>
<backgroundColor>-16777216</backgroundColor>
<lineWidth>1</lineWidth>
<points>
<point x="1458" y="2124"/>
<point x="411" y="1685"/>
</points>
</Connector>
<Connector class="oracle.dbtools.crest.swingui.relational.TVFKRelation" oid="7FBF66EE-A63D-11D5-0C37-8C0442C95D2C" otype="FKIndexAssociation" vid_source="6D6317DA-44EF-A756-0EC0-EA91C59F47C8" vid_target="F0E32C7A-CBA2-746F-3199-A7BE1C31A4EB">
<hideElementsInCurrentOnly>false</hideElementsInCurrentOnly>
<backgroundColor>-16777216</backgroundColor>
<lineWidth>1</lineWidth>
<points>
<point x="1543" y="2412"/>
<point x="636" y="570"/>
</points>
</Connector>
<Connector class="oracle.dbtools.crest.swingui.relational.TVFKRelation" oid="8019AF1D-3817-638D-21D8-9F6B826505F1" otype="FKIndexAssociation" vid_source="B735748C-5124-F6ED-005C-20C13B3441B1" vid_target="B8C6FE8F-86D3-D280-A906-C9920AB4BDBB">
<hideElementsInCurrentOnly>false</hideElementsInCurrentOnly>
<backgroundColor>-16777216</backgroundColor>
<lineWidth>1</lineWidth>
<points>
<point x="1000" y="1688"/>
<point x="3012" y="471"/>
</points>
</Connector>
<Connector class="oracle.dbtools.crest.swingui.relational.TVFKRelation" oid="8B2DA71C-E42C-1C5A-1313-AAF15AAEBC19" otype="FKIndexAssociation" vid_source="CB608AA3-00EB-16DE-4354-BC686D696C19" vid_target="A2B20561-DE2A-E6BA-E742-879918EB320C">
<hideElementsInCurrentOnly>false</hideElementsInCurrentOnly>
<backgroundColor>-16777216</backgroundColor>
<lineWidth>1</lineWidth>
<points>
<point x="499" y="2406"/>
<point x="441" y="217"/>
</points>
</Connector>
<Connector class="oracle.dbtools.crest.swingui.relational.TVFKRelation" oid="8E22D1B9-8515-DFBF-8083-0EC03D1F16B4" otype="FKIndexAssociation" vid_source="BC89369A-A176-92E8-4375-B85AC6B892D0" vid_target="386E014F-6611-2D63-FDE7-95E73A16772B">
<hideElementsInCurrentOnly>false</hideElementsInCurrentOnly>
<backgroundColor>-16777216</backgroundColor>
<lineWidth>1</lineWidth>
<points>
<point x="871" y="2385"/>
<point x="520" y="190"/>
</points>
</Connector>
<Connector class="oracle.dbtools.crest.swingui.relational.TVFKRelation" oid="91E62A72-397E-ECFE-A9A6-DF22D9BB3576" otype="FKIndexAssociation" vid_source="CB608AA3-00EB-16DE-4354-BC686D696C19" vid_target="D9E7CE60-0340-6CE2-FECF-ADCB687AC73A">
<hideElementsInCurrentOnly>false</hideElementsInCurrentOnly>
<backgroundColor>-16777216</backgroundColor>
<lineWidth>1</lineWidth>
<points>
<point x="473" y="2406"/>
<point x="1036" y="190"/>
</points>
</Connector>
<Connector class="oracle.dbtools.crest.swingui.relational.TVFKRelation" oid="929A4631-02D7-F734-A943-43673D82482D" otype="FKIndexAssociation" vid_source="BE4321F5-42BD-6777-870B-299897B5DEEB" vid_target="7E02EBD7-367D-B4FB-DDEF-C434EE2C17A1">
<hideElementsInCurrentOnly>false</hideElementsInCurrentOnly>
<backgroundColor>-16777216</backgroundColor>
<lineWidth>1</lineWidth>
<points>
<point x="1118" y="2092"/>
<point x="538" y="1051"/>
</points>
</Connector>
<Connector class="oracle.dbtools.crest.swingui.relational.TVFKRelation" oid="9404F223-29E6-C1F0-64C3-EBCED4FAE4E5" otype="FKIndexAssociation" vid_source="CB608AA3-00EB-16DE-4354-BC686D696C19" vid_target="5C66BF63-067C-1A42-715D-BD24198F0AAA">
<hideElementsInCurrentOnly>false</hideElementsInCurrentOnly>
<backgroundColor>-16777216</backgroundColor>
<lineWidth>1</lineWidth>
<points>
<point x="474" y="2406"/>
<point x="2190" y="188"/>
</points>
</Connector>
<Connector class="oracle.dbtools.crest.swingui.relational.TVFKRelation" oid="9654AC5C-14E0-23F0-658C-57B1389349B5" otype="FKIndexAssociation" vid_source="A91919A4-DA6F-3998-CC63-6A0AAAB7AA58" vid_target="F2BB0BB9-9C54-6BA9-58A2-658E8AFC55FD">
<hideElementsInCurrentOnly>false</hideElementsInCurrentOnly>
<backgroundColor>-16777216</backgroundColor>
<lineWidth>1</lineWidth>
<points>
<point x="2792" y="2416"/>
<point x="1405" y="1653"/>
</points>
</Connector>
<Connector class="oracle.dbtools.crest.swingui.relational.TVFKRelation" oid="9CB330D1-749A-1E1B-F3CB-6222E3262465" otype="FKIndexAssociation" vid_source="26599D9D-6C65-973C-5A2E-E323B9607EB2" vid_target="A7BC0044-8620-238E-B052-3FDB7F0346A3">
<hideElementsInCurrentOnly>false</hideElementsInCurrentOnly>
<backgroundColor>-16777216</backgroundColor>
<lineWidth>1</lineWidth>
<points>
<point x="3296" y="1477"/>
<point x="1416" y="616"/>
</points>
</Connector>
<Connector class="oracle.dbtools.crest.swingui.relational.TVFKRelation" oid="9D06210D-CC8E-28DD-33DE-2EB101C3905A" otype="FKIndexAssociation" vid_source="3E87ED0F-AF70-3B6B-B025-71DCF30FA07C" vid_target="A2B20561-DE2A-E6BA-E742-879918EB320C">
<hideElementsInCurrentOnly>false</hideElementsInCurrentOnly>
<backgroundColor>-16777216</backgroundColor>
<lineWidth>1</lineWidth>
<points>
<point x="80" y="2401"/>
<point x="441" y="153"/>
</points>
</Connector>
<Connector class="oracle.dbtools.crest.swingui.relational.TVFKRelation" oid="A141CA63-D9A3-3FFF-74FA-DC38A2591D9C" otype="FKIndexAssociation" vid_source="BC89369A-A176-92E8-4375-B85AC6B892D0" vid_target="A2B20561-DE2A-E6BA-E742-879918EB320C">
<hideElementsInCurrentOnly>false</hideElementsInCurrentOnly>
<backgroundColor>-16777216</backgroundColor>
<lineWidth>1</lineWidth>
<points>
<point x="1009" y="2385"/>
<point x="441" y="217"/>
</points>
</Connector>
<Connector class="oracle.dbtools.crest.swingui.relational.TVFKRelation" oid="A319D8C2-9629-1A1E-628E-8D1339AF7CF7" otype="FKIndexAssociation" vid_source="E3EEC2DC-DC2B-D990-7820-6452EAE5CC03" vid_target="B2F39D76-26E4-6529-A866-B4D0DC7269EF">
<hideElementsInCurrentOnly>false</hideElementsInCurrentOnly>
<backgroundColor>-16777216</backgroundColor>
<lineWidth>1</lineWidth>
<points>
<point x="153" y="1687"/>
<point x="153" y="1039"/>
</points>
</Connector>
<Connector class="oracle.dbtools.crest.swingui.relational.TVFKRelation" oid="A59E4709-E34D-0FF4-5E25-20F74433ACF2" otype="FKIndexAssociation" vid_source="A91919A4-DA6F-3998-CC63-6A0AAAB7AA58" vid_target="B2F39D76-26E4-6529-A866-B4D0DC7269EF">
<hideElementsInCurrentOnly>false</hideElementsInCurrentOnly>
<backgroundColor>-16777216</backgroundColor>
<lineWidth>1</lineWidth>
<points>
<point x="2790" y="2416"/>
<point x="269" y="1039"/>
</points>
</Connector>
<Connector class="oracle.dbtools.crest.swingui.relational.TVFKRelation" oid="A749B716-D793-6CB3-BAC3-D9C425E54350" otype="FKIndexAssociation" vid_source="E3EEC2DC-DC2B-D990-7820-6452EAE5CC03" vid_target="B8C6FE8F-86D3-D280-A906-C9920AB4BDBB">
<hideElementsInCurrentOnly>false</hideElementsInCurrentOnly>
<backgroundColor>-16777216</backgroundColor>
<lineWidth>1</lineWidth>
<points>
<point x="223" y="1687"/>
<point x="3012" y="471"/>
</points>
</Connector>
<Connector class="oracle.dbtools.crest.swingui.relational.TVFKRelation" oid="ACC643CC-CD60-545D-C7A1-F415F5C6709D" otype="FKIndexAssociation" vid_source="3E87ED0F-AF70-3B6B-B025-71DCF30FA07C" vid_target="F0E32C7A-CBA2-746F-3199-A7BE1C31A4EB">
<hideElementsInCurrentOnly>false</hideElementsInCurrentOnly>
<backgroundColor>-16777216</backgroundColor>
<lineWidth>1</lineWidth>
<points>
<point x="264" y="2401"/>
<point x="792" y="570"/>
</points>
</Connector>
<Connector class="oracle.dbtools.crest.swingui.relational.TVFKRelation" oid="B0F5F33F-D901-E10A-B616-0869651E7573" otype="FKIndexAssociation" vid_source="A91919A4-DA6F-3998-CC63-6A0AAAB7AA58" vid_target="7E02EBD7-367D-B4FB-DDEF-C434EE2C17A1">
<hideElementsInCurrentOnly>false</hideElementsInCurrentOnly>
<backgroundColor>-16777216</backgroundColor>
<lineWidth>1</lineWidth>
<points>
<point x="2792" y="2416"/>
<point x="538" y="1051"/>
</points>
</Connector>
<Connector class="oracle.dbtools.crest.swingui.relational.TVFKRelation" oid="B2770EA0-96D9-AEE8-8745-BA8BE7AB6ED3" otype="FKIndexAssociation" vid_source="6D6317DA-44EF-A756-0EC0-EA91C59F47C8" vid_target="B8C6FE8F-86D3-D280-A906-C9920AB4BDBB">
<hideElementsInCurrentOnly>false</hideElementsInCurrentOnly>
<backgroundColor>-16777216</backgroundColor>
<lineWidth>1</lineWidth>
<points>
<point x="1543" y="2412"/>
<point x="3012" y="471"/>
</points>
</Connector>
<Connector class="oracle.dbtools.crest.swingui.relational.TVFKRelation" oid="B2F16CC3-0E0A-9C8A-E470-99280FDD7572" otype="FKIndexAssociation" vid_source="3E87ED0F-AF70-3B6B-B025-71DCF30FA07C" vid_target="9B4D6AC3-1456-2BA8-F08B-273B777A7E2A">
<hideElementsInCurrentOnly>false</hideElementsInCurrentOnly>
<backgroundColor>-16777216</backgroundColor>
<lineWidth>1</lineWidth>
<points>
<point x="264" y="2401"/>
<point x="2228" y="622"/>
</points>
</Connector>
<Connector class="oracle.dbtools.crest.swingui.relational.TVFKRelation" oid="B43B4875-1E8B-F593-AF9A-BF87DAEF5B93" otype="FKIndexAssociation" vid_source="BC89369A-A176-92E8-4375-B85AC6B892D0" vid_target="B432C446-685E-8118-0B87-3EF3C04631BF">
<hideElementsInCurrentOnly>false</hideElementsInCurrentOnly>
<backgroundColor>-16777216</backgroundColor>
<lineWidth>1</lineWidth>
<points>
<point x="778" y="2385"/>
<point x="1149" y="1044"/>
</points>
</Connector>
<Connector class="oracle.dbtools.crest.swingui.relational.TVFKRelation" oid="B637B021-8E8A-747A-3EFD-CCC4B6865993" otype="FKIndexAssociation" vid_source="BC89369A-A176-92E8-4375-B85AC6B892D0" vid_target="F0E32C7A-CBA2-746F-3199-A7BE1C31A4EB">
<hideElementsInCurrentOnly>false</hideElementsInCurrentOnly>
<backgroundColor>-16777216</backgroundColor>
<lineWidth>1</lineWidth>
<points>
<point x="778" y="2385"/>
<point x="751" y="570"/>
</points>
</Connector>
<Connector class="oracle.dbtools.crest.swingui.relational.TVFKRelation" oid="B9A19469-34CD-5150-D313-6061F315741A" otype="FKIndexAssociation" vid_source="3E87ED0F-AF70-3B6B-B025-71DCF30FA07C" vid_target="26599D9D-6C65-973C-5A2E-E323B9607EB2">
<hideElementsInCurrentOnly>false</hideElementsInCurrentOnly>
<backgroundColor>-16777216</backgroundColor>
<lineWidth>1</lineWidth>
<points>
<point x="264" y="2401"/>
<point x="3296" y="1633"/>
</points>
</Connector>
<Connector class="oracle.dbtools.crest.swingui.relational.TVFKRelation" oid="BAA0E2B0-4FE8-3428-C100-3EA7B563357B" otype="FKIndexAssociation" vid_source="EF9E83AB-D9CE-C610-6AF9-2D88CAE5BF84" vid_target="B2F39D76-26E4-6529-A866-B4D0DC7269EF">
<hideElementsInCurrentOnly>false</hideElementsInCurrentOnly>
<backgroundColor>-16777216</backgroundColor>
<lineWidth>1</lineWidth>
<points>
<point x="2058" y="2431"/>
<point x="235" y="1039"/>
</points>
</Connector>
<Connector class="oracle.dbtools.crest.swingui.relational.TVFKRelation" oid="BF12D5E4-D792-3A67-7595-A0E9E5864369" otype="FKIndexAssociation" vid_source="BE4321F5-42BD-6777-870B-299897B5DEEB" vid_target="49354C52-3926-3594-CB4B-7DA72E65D14E">
<hideElementsInCurrentOnly>false</hideElementsInCurrentOnly>
<backgroundColor>-16777216</backgroundColor>
<lineWidth>1</lineWidth>
<points>
<point x="1118" y="2092"/>
<point x="411" y="1685"/>
</points>
</Connector>
<Connector class="oracle.dbtools.crest.swingui.relational.TVFKRelation" oid="C5681544-51E3-4DA7-1B68-15A6FECBCF8B" otype="FKIndexAssociation" vid_source="C7B173EB-649C-B128-AB08-14E43E042660" vid_target="B8C6FE8F-86D3-D280-A906-C9920AB4BDBB">
<hideElementsInCurrentOnly>false</hideElementsInCurrentOnly>
<backgroundColor>-16777216</backgroundColor>
<lineWidth>1</lineWidth>
<points>
<point x="1458" y="2124"/>
<point x="3012" y="471"/>
</points>
</Connector>
<Connector class="oracle.dbtools.crest.swingui.relational.TVFKRelation" oid="CB41E983-08E2-3676-3E3F-4916214CB782" otype="FKIndexAssociation" vid_source="E3EEC2DC-DC2B-D990-7820-6452EAE5CC03" vid_target="F0E32C7A-CBA2-746F-3199-A7BE1C31A4EB">
<hideElementsInCurrentOnly>false</hideElementsInCurrentOnly>
<backgroundColor>-16777216</backgroundColor>
<lineWidth>1</lineWidth>
<points>
<point x="225" y="1687"/>
<point x="771" y="570"/>
</points>
</Connector>
<Connector class="oracle.dbtools.crest.swingui.relational.TVFKRelation" oid="CEBE1F1B-67B3-D3EF-8120-501088041074" otype="FKIndexAssociation" vid_source="BE4321F5-42BD-6777-870B-299897B5DEEB" vid_target="B8C6FE8F-86D3-D280-A906-C9920AB4BDBB">
<hideElementsInCurrentOnly>false</hideElementsInCurrentOnly>
<backgroundColor>-16777216</backgroundColor>
<lineWidth>1</lineWidth>
<points>
<point x="1118" y="2092"/>
<point x="3012" y="471"/>
</points>
</Connector>
<Connector class="oracle.dbtools.crest.swingui.relational.TVFKRelation" oid="D13C28D7-60DA-6620-D715-3B5083A7405F" otype="FKIndexAssociation" vid_source="6D6317DA-44EF-A756-0EC0-EA91C59F47C8" vid_target="AA93D5A3-02D5-C622-8083-E4FA183000B2">
<hideElementsInCurrentOnly>false</hideElementsInCurrentOnly>
<backgroundColor>-16777216</backgroundColor>
<lineWidth>1</lineWidth>
<points>
<point x="1542" y="2412"/>
<point x="2735" y="188"/>
</points>
</Connector>
<Connector class="oracle.dbtools.crest.swingui.relational.TVFKRelation" oid="D2E4E7F3-EE15-B05B-76FE-CCF05BD6123A" otype="FKIndexAssociation" vid_source="DD4F4BB5-CF62-D62E-4744-EEF2B5E4C96A" vid_target="B8C6FE8F-86D3-D280-A906-C9920AB4BDBB">
<hideElementsInCurrentOnly>false</hideElementsInCurrentOnly>
<backgroundColor>-16777216</backgroundColor>
<lineWidth>1</lineWidth>
<points>
<point x="157" y="2095"/>
<point x="3012" y="471"/>
</points>
</Connector>
<Connector class="oracle.dbtools.crest.swingui.relational.TVFKRelation" oid="D3A91102-9FF6-2515-6CE9-73BAEB820A29" otype="FKIndexAssociation" vid_source="3E87ED0F-AF70-3B6B-B025-71DCF30FA07C" vid_target="64D78C5C-398E-3F88-E026-222A3DD14985">
<hideElementsInCurrentOnly>false</hideElementsInCurrentOnly>
<backgroundColor>-16777216</backgroundColor>
<lineWidth>1</lineWidth>
<points>
<point x="198" y="2401"/>
<point x="198" y="575"/>
</points>
</Connector>
<Connector class="oracle.dbtools.crest.swingui.relational.TVFKRelation" oid="D3F837B5-E3DC-D0FF-0C16-DAB8AB92008B" otype="FKIndexAssociation" vid_source="C7B173EB-649C-B128-AB08-14E43E042660" vid_target="B432C446-685E-8118-0B87-3EF3C04631BF">
<hideElementsInCurrentOnly>false</hideElementsInCurrentOnly>
<backgroundColor>-16777216</backgroundColor>
<lineWidth>1</lineWidth>
<points>
<point x="1458" y="2124"/>
<point x="1057" y="1044"/>
</points>
</Connector>
<Connector class="oracle.dbtools.crest.swingui.relational.TVFKRelation" oid="D57CF6E0-C9F2-9DB3-306F-540ADE3C3D3A" otype="FKIndexAssociation" vid_source="3E87ED0F-AF70-3B6B-B025-71DCF30FA07C" vid_target="56DF83AF-3665-104E-85B4-92B7C8B1BF3F">
<hideElementsInCurrentOnly>false</hideElementsInCurrentOnly>
<backgroundColor>-16777216</backgroundColor>
<lineWidth>1</lineWidth>
<points>
<point x="264" y="2401"/>
<point x="1722" y="1074"/>
</points>
</Connector>
<Connector class="oracle.dbtools.crest.swingui.relational.TVFKRelation" oid="D75CDCA4-7DD5-7898-1266-1BB26650A9F5" otype="FKIndexAssociation" vid_source="7DB9CAC1-0900-E28B-89D7-70F157D2C798" vid_target="B8C6FE8F-86D3-D280-A906-C9920AB4BDBB">
<hideElementsInCurrentOnly>false</hideElementsInCurrentOnly>
<backgroundColor>-16777216</backgroundColor>
<lineWidth>1</lineWidth>
<points>
<point x="1796" y="2124"/>
<point x="3012" y="637"/>
</points>
</Connector>
<Connector class="oracle.dbtools.crest.swingui.relational.TVFKRelation" oid="DA56DDCB-ECAA-733B-3784-8009B6BEA581" otype="FKIndexAssociation" vid_source="6D6317DA-44EF-A756-0EC0-EA91C59F47C8" vid_target="64D78C5C-398E-3F88-E026-222A3DD14985">
<hideElementsInCurrentOnly>false</hideElementsInCurrentOnly>
<backgroundColor>-16777216</backgroundColor>
<lineWidth>1</lineWidth>
<points>
<point x="1544" y="2412"/>
<point x="246" y="575"/>
</points>
</Connector>
<Connector class="oracle.dbtools.crest.swingui.relational.TVFKRelation" oid="DB5BA6C0-1F84-FBC5-2007-BB86AE431473" otype="FKIndexAssociation" vid_source="B8C6FE8F-86D3-D280-A906-C9920AB4BDBB" vid_target="C3F2C83A-0A03-314B-B41C-001C97FC4B34">
<hideElementsInCurrentOnly>false</hideElementsInCurrentOnly>
<backgroundColor>-16777216</backgroundColor>
<lineWidth>1</lineWidth>
<points>
<point x="3012" y="471"/>
<point x="3551" y="135"/>
</points>
</Connector>
<Connector class="oracle.dbtools.crest.swingui.relational.TVFKRelation" oid="DB6E00BF-EB23-2019-E93B-C18B021C4ED9" otype="FKIndexAssociation" vid_source="A91919A4-DA6F-3998-CC63-6A0AAAB7AA58" vid_target="B432C446-685E-8118-0B87-3EF3C04631BF">
<hideElementsInCurrentOnly>false</hideElementsInCurrentOnly>
<backgroundColor>-16777216</backgroundColor>
<lineWidth>1</lineWidth>
<points>
<point x="2791" y="2416"/>
<point x="1057" y="1044"/>
</points>
</Connector>
<Connector class="oracle.dbtools.crest.swingui.relational.TVFKRelation" oid="DC9D5628-C556-464E-5735-38B51B9C4EF0" otype="FKIndexAssociation" vid_source="927C5CC2-2227-D7D4-82D8-4E2BE921A317" vid_target="B2F39D76-26E4-6529-A866-B4D0DC7269EF">
<hideElementsInCurrentOnly>false</hideElementsInCurrentOnly>
<backgroundColor>-16777216</backgroundColor>
<lineWidth>1</lineWidth>
<points>
<point x="492" y="2118"/>
<point x="198" y="1039"/>
</points>
</Connector>
<Connector class="oracle.dbtools.crest.swingui.relational.TVFKRelation" oid="E4246921-5A1B-F7FE-947B-48E9D2E7B57A" otype="FKIndexAssociation" vid_source="BC89369A-A176-92E8-4375-B85AC6B892D0" vid_target="9B4D6AC3-1456-2BA8-F08B-273B777A7E2A">
<hideElementsInCurrentOnly>false</hideElementsInCurrentOnly>
<backgroundColor>-16777216</backgroundColor>
<lineWidth>1</lineWidth>
<points>
<point x="871" y="2385"/>
<point x="2228" y="561"/>
</points>
</Connector>
<Connector class="oracle.dbtools.crest.swingui.relational.TVFKRelation" oid="E444B137-CC52-E54C-97DE-A07177FE3B1C" otype="FKIndexAssociation" vid_source="26599D9D-6C65-973C-5A2E-E323B9607EB2" vid_target="B8C6FE8F-86D3-D280-A906-C9920AB4BDBB">
<hideElementsInCurrentOnly>false</hideElementsInCurrentOnly>
<backgroundColor>-16777216</backgroundColor>
<lineWidth>1</lineWidth>
<points>
<point x="3296" y="1617"/>
<point x="3012" y="471"/>
</points>
</Connector>
<Connector class="oracle.dbtools.crest.swingui.relational.TVFKRelation" oid="E8582FBD-C119-D614-81AF-6785FA6575FF" otype="FKIndexAssociation" vid_source="6D6317DA-44EF-A756-0EC0-EA91C59F47C8" vid_target="9B4D6AC3-1456-2BA8-F08B-273B777A7E2A">
<hideElementsInCurrentOnly>false</hideElementsInCurrentOnly>
<backgroundColor>-16777216</backgroundColor>
<lineWidth>1</lineWidth>
<points>
<point x="1543" y="2412"/>
<point x="2228" y="561"/>
</points>
</Connector>
<Connector class="oracle.dbtools.crest.swingui.relational.TVFKRelation" oid="EA31C9B6-38FD-387E-098A-9A7F915FFCF6" otype="FKIndexAssociation" vid_source="A91919A4-DA6F-3998-CC63-6A0AAAB7AA58" vid_target="64D78C5C-398E-3F88-E026-222A3DD14985">
<hideElementsInCurrentOnly>false</hideElementsInCurrentOnly>
<backgroundColor>-16777216</backgroundColor>
<lineWidth>1</lineWidth>
<points>
<point x="2792" y="2416"/>
<point x="316" y="575"/>
</points>
</Connector>
<Connector class="oracle.dbtools.crest.swingui.relational.TVFKRelation" oid="EB867477-014D-E578-82EB-4D9283439E56" otype="FKIndexAssociation" vid_source="3E87ED0F-AF70-3B6B-B025-71DCF30FA07C" vid_target="B2F39D76-26E4-6529-A866-B4D0DC7269EF">
<hideElementsInCurrentOnly>false</hideElementsInCurrentOnly>
<backgroundColor>-16777216</backgroundColor>
<lineWidth>1</lineWidth>
<points>
<point x="138" y="2401"/>
<point x="138" y="1039"/>
</points>
</Connector>
<Connector class="oracle.dbtools.crest.swingui.relational.TVFKRelation" oid="F3799A8C-EEF3-D51B-CFD1-AF125EC1510B" otype="FKIndexAssociation" vid_source="CB608AA3-00EB-16DE-4354-BC686D696C19" vid_target="9B4D6AC3-1456-2BA8-F08B-273B777A7E2A">
<hideElementsInCurrentOnly>false</hideElementsInCurrentOnly>
<backgroundColor>-16777216</backgroundColor>
<lineWidth>1</lineWidth>
<points>
<point x="473" y="2406"/>
<point x="2228" y="561"/>
</points>
</Connector>
<Connector class="oracle.dbtools.crest.swingui.relational.TVFKRelation" oid="F5D8AE01-7774-B1C9-B7B1-D7A92A826C93" otype="FKIndexAssociation" vid_source="CB608AA3-00EB-16DE-4354-BC686D696C19" vid_target="A7BC0044-8620-238E-B052-3FDB7F0346A3">
<hideElementsInCurrentOnly>false</hideElementsInCurrentOnly>
<backgroundColor>-16777216</backgroundColor>
<lineWidth>1</lineWidth>
<points>
<point x="473" y="2406"/>
<point x="1416" y="546"/>
</points>
</Connector>
<Connector class="oracle.dbtools.crest.swingui.relational.TVFKRelation" oid="F693EADB-0C80-B953-7A8B-C92C2C26B1A4" otype="FKIndexAssociation" vid_source="3E87ED0F-AF70-3B6B-B025-71DCF30FA07C" vid_target="D9E7CE60-0340-6CE2-FECF-ADCB687AC73A">
<hideElementsInCurrentOnly>false</hideElementsInCurrentOnly>
<backgroundColor>-16777216</backgroundColor>
<lineWidth>1</lineWidth>
<points>
<point x="264" y="2401"/>
<point x="1036" y="160"/>
</points>
</Connector>
<Connector class="oracle.dbtools.crest.swingui.relational.TVFKRelation" oid="F8895C45-AE93-7180-655D-3D54C17D478E" otype="FKIndexAssociation" vid_source="F2BB0BB9-9C54-6BA9-58A2-658E8AFC55FD" vid_target="B8C6FE8F-86D3-D280-A906-C9920AB4BDBB">
<hideElementsInCurrentOnly>false</hideElementsInCurrentOnly>
<backgroundColor>-16777216</backgroundColor>
<lineWidth>1</lineWidth>
<points>
<point x="1454" y="1653"/>
<point x="3012" y="471"/>
</points>
</Connector>
<Connector class="oracle.dbtools.crest.swingui.relational.TVFKRelation" oid="FC472D28-8AF5-FC37-2829-670B8C909676" otype="FKIndexAssociation" vid_source="26599D9D-6C65-973C-5A2E-E323B9607EB2" vid_target="56DF83AF-3665-104E-85B4-92B7C8B1BF3F">
<hideElementsInCurrentOnly>false</hideElementsInCurrentOnly>
<backgroundColor>-16777216</backgroundColor>
<lineWidth>1</lineWidth>
<points>
<point x="3296" y="1612"/>
<point x="1653" y="1074"/>
</points>
</Connector>
<Connector class="oracle.dbtools.crest.swingui.relational.TVFKRelation" oid="FFF4AA17-CC38-6165-C5B8-AF5F2C47EE5F" otype="FKIndexAssociation" vid_source="BC89369A-A176-92E8-4375-B85AC6B892D0" vid_target="5C66BF63-067C-1A42-715D-BD24198F0AAA">
<hideElementsInCurrentOnly>false</hideElementsInCurrentOnly>
<backgroundColor>-16777216</backgroundColor>
<lineWidth>1</lineWidth>
<points>
<point x="872" y="2385"/>
<point x="2190" y="188"/>
</points>
</Connector>
</connectors>
</Diagram>
