<?xml version = '1.0' encoding = 'UTF-8'?>
<Entity class="oracle.dbtools.crest.model.design.logical.Entity" directorySegmentName="seg_3" id="7400A8E2-85CE-63B9-9E80-306F4688813F" name="league">
<createdBy>leads</createdBy>
<createdTime>2026-03-12 07:48:51 UTC</createdTime>
<ownerDesignName>leadsuser</ownerDesignName>
<importedID>2F3102BF-AC16-B6CD-EFF4-837303A68C4A</importedID>
<engineerTo>
<item key="D0ADEC0C-0B6F-9EE3-0047-804409B8E385" value="true"/>
</engineerTo>
<adequatelyNormalized>NO</adequatelyNormalized>
<expectedVolumes>0</expectedVolumes>
<fwdEngineeringStrategyName>Single Table</fwdEngineeringStrategyName>
<growthPercent>0</growthPercent>
<growthType>Year</growthType>
<maxVolumes>9999999</maxVolumes>
<minVolumes>0</minVolumes>
<normalForm>Third</normalForm>
<preferredAbbreviation>league</preferredAbbreviation>
<shortName>league</shortName>
<synonym>league</synonym>
<synonymToDisplay>league</synonymToDisplay>
<attributes itemClass="oracle.dbtools.crest.model.design.logical.Attribute">
<Attribute name="code" id="8285ACBF-5A1F-439A-91AE-0AED50B6E704">
<createdBy>leads</createdBy>
<createdTime>2026-03-12 07:48:53 UTC</createdTime>
<comment><![CDATA[League Code - CANDIDATE/EMPLOYEE]]></comment>
<commentInRDBMS><![CDATA[League Code - CANDIDATE/EMPLOYEE]]></commentInRDBMS>
<notes><![CDATA[League Code - CANDIDATE/EMPLOYEE]]></notes>
<ownerDesignName>leadsuser</ownerDesignName>
<importedID>C7567DC4-A124-F400-15DA-B8C64FD3872B</importedID>
<engineerTo>
<item key="D0ADEC0C-0B6F-9EE3-0047-804409B8E385" value="true"/>
</engineerTo>
<useDomainConstraints>false</useDomainConstraints>
<use>1</use>
<ownDataTypeParameters>,,</ownDataTypeParameters>
</Attribute>
<Attribute name="name" id="B5511117-9D77-17BF-7AF9-69EB3F8EDDEA">
<createdBy>leads</createdBy>
<createdTime>2026-03-12 07:48:53 UTC</createdTime>
<ownerDesignName>leadsuser</ownerDesignName>
<importedID>0B61DAB2-EAFC-2095-F54A-637CEEB452BC</importedID>
<engineerTo>
<item key="D0ADEC0C-0B6F-9EE3-0047-804409B8E385" value="true"/>
</engineerTo>
<useDomainConstraints>false</useDomainConstraints>
<use>1</use>
<ownDataTypeParameters>,,</ownDataTypeParameters>
</Attribute>
<Attribute name="descriptions" id="1A025D4E-6B53-7A45-2AB1-30478A1C0ECB">
<createdBy>leads</createdBy>
<createdTime>2026-03-12 07:48:53 UTC</createdTime>
<comment><![CDATA[performance parameter description]]></comment>
<commentInRDBMS><![CDATA[performance parameter description]]></commentInRDBMS>
<ownerDesignName>leadsuser</ownerDesignName>
<importedID>06973164-B82F-8CC7-DBC7-5C0A2BF9395D</importedID>
<engineerTo>
<item key="D0ADEC0C-0B6F-9EE3-0047-804409B8E385" value="true"/>
</engineerTo>
<nullsAllowed>true</nullsAllowed>
<useDomainConstraints>false</useDomainConstraints>
<use>0</use>
<logicalDatatype>LOGDT024</logicalDatatype>
<domain>D8145389-4D0D-CC31-9923-FD4288ACF409</domain>
<ownDataTypeParameters>,,</ownDataTypeParameters>
<propertyMap>
<property name="engineerTo" value=""/>
</propertyMap>
</Attribute>
</attributes>
<identifiers itemClass="oracle.dbtools.crest.model.design.logical.CandidateKey">
<identifier id="BFD0EF9E-42F5-8ABD-7F76-A6AF9ABBD045" name="league_PK">
<createdBy>leads</createdBy>
<createdTime>2026-03-12 07:48:53 UTC</createdTime>
<ownerDesignName>leadsuser</ownerDesignName>
<shouldEngineer>false</shouldEngineer>
<importedID>B0A11A10-48F3-6585-96CA-5B9BD8784350</importedID>
<engineerTo>
<item key="D0ADEC0C-0B6F-9EE3-0047-804409B8E385" value="false"/>
</engineerTo>
<pk>true</pk>
<usedAttributes>
<attributeRef>8285ACBF-5A1F-439A-91AE-0AED50B6E704</attributeRef>
</usedAttributes>
</identifier>
<identifier id="6C11C4EE-E412-5E2B-6303-FED275BE7297" name="league_UN">
<createdBy>leads</createdBy>
<createdTime>2026-03-12 07:48:53 UTC</createdTime>
<ownerDesignName>leadsuser</ownerDesignName>
<shouldEngineer>false</shouldEngineer>
<importedID>44DAF815-7A9E-FC24-D0D9-42396293331F</importedID>
<engineerTo>
<item key="D0ADEC0C-0B6F-9EE3-0047-804409B8E385" value="false"/>
</engineerTo>
<usedAttributes>
<attributeRef>B5511117-9D77-17BF-7AF9-69EB3F8EDDEA</attributeRef>
</usedAttributes>
</identifier>
</identifiers>
</Entity>
